{"frames": {

"01.png":
{
	"frame": {"x":1,"y":1,"w":50,"h":50},
	"rotated": false,
	"trimmed": false,
	"spriteSourceSize": {"x":0,"y":0,"w":50,"h":50},
	"sourceSize": {"w":50,"h":50}
},
"02.png":
{
	"frame": {"x":53,"y":1,"w":50,"h":50},
	"rotated": false,
	"trimmed": false,
	"spriteSourceSize": {"x":0,"y":0,"w":50,"h":50},
	"sourceSize": {"w":50,"h":50}
},
"03.png":
{
	"frame": {"x":105,"y":1,"w":50,"h":50},
	"rotated": false,
	"trimmed": false,
	"spriteSourceSize": {"x":0,"y":0,"w":50,"h":50},
	"sourceSize": {"w":50,"h":50}
},
"04.png":
{
	"frame": {"x":157,"y":1,"w":50,"h":50},
	"rotated": false,
	"trimmed": false,
	"spriteSourceSize": {"x":0,"y":0,"w":50,"h":50},
	"sourceSize": {"w":50,"h":50}
},
"05.png":
{
	"frame": {"x":209,"y":1,"w":50,"h":50},
	"rotated": false,
	"trimmed": false,
	"spriteSourceSize": {"x":0,"y":0,"w":50,"h":50},
	"sourceSize": {"w":50,"h":50}
},
"06.png":
{
	"frame": {"x":261,"y":1,"w":50,"h":50},
	"rotated": false,
	"trimmed": false,
	"spriteSourceSize": {"x":0,"y":0,"w":50,"h":50},
	"sourceSize": {"w":50,"h":50}
},
"07.png":
{
	"frame": {"x":313,"y":1,"w":50,"h":50},
	"rotated": false,
	"trimmed": false,
	"spriteSourceSize": {"x":0,"y":0,"w":50,"h":50},
	"sourceSize": {"w":50,"h":50}
},
"08.png":
{
	"frame": {"x":365,"y":1,"w":50,"h":50},
	"rotated": false,
	"trimmed": false,
	"spriteSourceSize": {"x":0,"y":0,"w":50,"h":50},
	"sourceSize": {"w":50,"h":50}
},
"09.png":
{
	"frame": {"x":417,"y":1,"w":50,"h":50},
	"rotated": false,
	"trimmed": false,
	"spriteSourceSize": {"x":0,"y":0,"w":50,"h":50},
	"sourceSize": {"w":50,"h":50}
},
"10.png":
{
	"frame": {"x":469,"y":1,"w":50,"h":50},
	"rotated": false,
	"trimmed": false,
	"spriteSourceSize": {"x":0,"y":0,"w":50,"h":50},
	"sourceSize": {"w":50,"h":50}
},
"11.png":
{
	"frame": {"x":521,"y":1,"w":50,"h":50},
	"rotated": false,
	"trimmed": false,
	"spriteSourceSize": {"x":0,"y":0,"w":50,"h":50},
	"sourceSize": {"w":50,"h":50}
},
"12.png":
{
	"frame": {"x":573,"y":1,"w":50,"h":50},
	"rotated": false,
	"trimmed": false,
	"spriteSourceSize": {"x":0,"y":0,"w":50,"h":50},
	"sourceSize": {"w":50,"h":50}
},
"13.png":
{
	"frame": {"x":625,"y":1,"w":50,"h":50},
	"rotated": false,
	"trimmed": false,
	"spriteSourceSize": {"x":0,"y":0,"w":50,"h":50},
	"sourceSize": {"w":50,"h":50}
},
"14.png":
{
	"frame": {"x":677,"y":1,"w":50,"h":50},
	"rotated": false,
	"trimmed": false,
	"spriteSourceSize": {"x":0,"y":0,"w":50,"h":50},
	"sourceSize": {"w":50,"h":50}
},
"15.png":
{
	"frame": {"x":729,"y":1,"w":50,"h":50},
	"rotated": false,
	"trimmed": false,
	"spriteSourceSize": {"x":0,"y":0,"w":50,"h":50},
	"sourceSize": {"w":50,"h":50}
},
"16.png":
{
	"frame": {"x":781,"y":1,"w":50,"h":50},
	"rotated": false,
	"trimmed": false,
	"spriteSourceSize": {"x":0,"y":0,"w":50,"h":50},
	"sourceSize": {"w":50,"h":50}
}},
"meta": {
	"app": "http://www.codeandweb.com/texturepacker",
	"version": "1.0",
	"image": "pokebol_sprite.png",
	"format": "RGBA8888",
	"size": {"w":832,"h":52},
	"scale": "1",
	"smartupdate": "$TexturePacker:SmartUpdate:c09999ef122b0288b4ed9abe87e0a653:983ad6dfb206a3615258e195f732b74e:fbe6bcc9bce4d2a7dfd92d6b36292868$"
}
}
